tiledb/cf/__init__.py
tiledb/cf/__main__.py
tiledb/cf/_utils.py
tiledb/cf/cli.py
tiledb/cf/testing.py
tiledb/cf/core/__init__.py
tiledb/cf/core/_array_creator.py
tiledb/cf/core/_attr_creator.py
tiledb/cf/core/_dataspace_creator.py
tiledb/cf/core/_dim_creator.py
tiledb/cf/core/_fragment_writer.py
tiledb/cf/core/_metadata.py
tiledb/cf/core/_shared_dim.py
tiledb/cf/core/api.py
tiledb/cf/core/registry.py
tiledb/cf/core/source.py
tiledb/cf/netcdf_engine/__init__.py
tiledb/cf/netcdf_engine/_array_converters.py
tiledb/cf/netcdf_engine/_attr_converters.py
tiledb/cf/netcdf_engine/_dim_converters.py
tiledb/cf/netcdf_engine/_utils.py
tiledb/cf/netcdf_engine/api.py
tiledb/cf/netcdf_engine/converter.py
tiledb/cf/xarray_engine/__init__.py
tiledb/cf/xarray_engine/_array_wrapper.py
tiledb/cf/xarray_engine/_backend_store.py
tiledb/cf/xarray_engine/_common.py
tiledb/cf/xarray_engine/_deprecated_backend_store.py
tiledb/cf/xarray_engine/_encoding.py
tiledb/cf/xarray_engine/_writer.py
tiledb/cf/xarray_engine/api.py
tiledb/cf/xarray_engine/engine.py
tiledb_cf-0.9.1.dist-info/LICENSE
tiledb_cf-0.9.1.dist-info/METADATA
tiledb_cf-0.9.1.dist-info/WHEEL
tiledb_cf-0.9.1.dist-info/entry_points.txt
tiledb_cf-0.9.1.dist-info/top_level.txt
tiledb_cf-0.9.1.dist-info/RECORD
