Metadata-Version: 2.1
Name: tiledb-cf
Version: 0.9.1
Summary: TileDB Python library for supporting Climate and Forecast datasets.
Home-page: https://github.com/TileDB-Inc/TileDB-CF-Py
Author: TileDB, Inc.
Author-email: help@tiledb.io
License: MIT
Project-URL: Documentation, https://docs.tiledb.com
Keywords: tiledb,climate,forecast,netcdf
Classifier: Development Status :: 3 - Alpha
Classifier: Intended Audience :: Developers
Classifier: Intended Audience :: Information Technology
Classifier: Intended Audience :: Science/Research
Classifier: License :: OSI Approved :: MIT License
Classifier: Operating System :: OS Independent
Classifier: Programming Language :: Python :: 3
Classifier: Programming Language :: Python :: 3.7
Classifier: Programming Language :: Python :: 3.8
Classifier: Programming Language :: Python :: 3.9
Classifier: Programming Language :: Python :: Implementation :: PyPy
Classifier: Topic :: Software Development
Requires-Python: >=3.7
License-File: LICENSE
Requires-Dist: numpy >=1.16.5
Requires-Dist: setuptools >=40.4
Requires-Dist: tiledb >=0.21.2
Requires-Dist: click >=0.7.0
Requires-Dist: typing-extensions >=4.0.0
Provides-Extra: complete
Requires-Dist: netCDF4 ; extra == 'complete'
Requires-Dist: xarray >=0.18.0 ; extra == 'complete'
Requires-Dist: dask[complete] ; extra == 'complete'
Provides-Extra: docs
Requires-Dist: quartodoc ; extra == 'docs'
Requires-Dist: matplotlib ; extra == 'docs'
Requires-Dist: jupyter ; extra == 'docs'
Requires-Dist: netCDF4 ; extra == 'docs'
Requires-Dist: xarray >=0.18.0 ; extra == 'docs'
Requires-Dist: dask[complete] ; extra == 'docs'
Provides-Extra: netcdf4
Requires-Dist: netCDF4 ; extra == 'netcdf4'
Provides-Extra: parallel
Requires-Dist: dask[complete] ; extra == 'parallel'
Provides-Extra: xarray
Requires-Dist: xarray >=0.18.0 ; extra == 'xarray'
